palconfig/__init__.py
palconfig/cli.py
palconfig/codec.py
palconfig/schema.py
palconfig-0.1.0.dist-info/METADATA
palconfig-0.1.0.dist-info/WHEEL
palconfig-0.1.0.dist-info/entry_points.txt
palconfig-0.1.0.dist-info/RECORD
