Metadata-Version: 2.4
Name: palconfig
Version: 0.1.0
Summary: Utility for serialization and parsing of Palworld configuration files
Author: DJ Stomp
Author-email: 85457381+DJStompZone@users.noreply.github.com
Requires-Python: >=3.10,<4.0
Classifier: Programming Language :: Python :: 3
Classifier: Programming Language :: Python :: 3.10
Classifier: Programming Language :: Python :: 3.11
Classifier: Programming Language :: Python :: 3.12
Classifier: Programming Language :: Python :: 3.13
Classifier: Programming Language :: Python :: 3.14
